diarizationlm/__init__.py
diarizationlm/levenshtein.py
diarizationlm/levenshtein_test.py
diarizationlm/metrics.py
diarizationlm/metrics_test.py
diarizationlm/utils.py
diarizationlm/utils_test.py
diarizationlm-0.1.5.dist-info/METADATA
diarizationlm-0.1.5.dist-info/WHEEL
diarizationlm-0.1.5.dist-info/top_level.txt
diarizationlm-0.1.5.dist-info/RECORD
