Metadata-Version: 2.1
Name: diarizationlm
Version: 0.1.5
Summary: DiarizationLM
Home-page: https://github.com/google/speaker-id/tree/master/DiarizationLM
Author: Quan Wang
Author-email: quanw@google.com
Classifier: Programming Language :: Python :: 3
Classifier: License :: OSI Approved :: Apache Software License
Classifier: Operating System :: OS Independent
Requires-Dist: numpy
Requires-Dist: numba
Requires-Dist: scipy
Requires-Dist: tensorflow-text
Requires-Dist: absl-py
Requires-Dist: openai
Requires-Dist: datasets
Requires-Dist: tqdm
Requires-Dist: colortimelog
Requires-Dist: word-levenshtein
